cacophonyapi/__init__.py
cacophonyapi/apibase.py
cacophonyapi/config.py
cacophonyapi/device.py
cacophonyapi/user.py
cacophonyapi/test/__init__.py
cacophonyapi/test/test_client_user_with_server.py
cacophonyapi/test/test_client_user_without_server.py
cacophonyapi-0.0.5.dist-info/licenses/LICENSE
cacophonyapi-0.0.5.dist-info/METADATA
cacophonyapi-0.0.5.dist-info/WHEEL
cacophonyapi-0.0.5.dist-info/top_level.txt
cacophonyapi-0.0.5.dist-info/RECORD
