Metadata-Version: 2.4
Name: cacophonyapi
Version: 0.0.5
Summary: Cacophony Project REST API client for Python
Home-page: https://github.com/TheCacophonyProject/python-api
Author: Anthony Uphof, Giampaolo Ferraro, Cameron Ryan-Pears, Menno Finlay-Smits
Author-email: coredev@cacophony.org.nz
License: GNU AFFERO GENERAL PUBLIC License 3 19 November 2007
Project-URL: Bug Tracker, https://github.com/TheCacophonyProject/python-api
Project-URL: Documentation, https://docs.cacophony.org.nz
Project-URL: Source Code, https://github.com/TheCacophonyProject/python-api
Keywords: cacophonyproject api client rest
Classifier: Development Status :: 4 - Beta
Classifier: Intended Audience :: Developers
Classifier: License :: OSI Approved :: Apache Software License
Classifier: Operating System :: OS Independent
Classifier: Programming Language :: Python
Classifier: Programming Language :: Python :: 3.6
Classifier: Programming Language :: Python :: 3.7
Classifier: Topic :: Software Development :: Libraries
Classifier: Topic :: Software Development :: Libraries :: Python Modules
License-File: LICENSE
Requires-Dist: requests>=2.20.0
Requires-Dist: requests-toolbelt~=0.9.1
Provides-Extra: test
Requires-Dist: pytest~=5.2.2; extra == "test"
Requires-Dist: nose2; extra == "test"
Requires-Dist: nose2[coverage-plugin]~=0.6.5; extra == "test"
Requires-Dist: mock; extra == "test"
Requires-Dist: mock-open~=1.3.1; extra == "test"
Requires-Dist: requests-mock; extra == "test"
Requires-Dist: coverage~=4.5.4; extra == "test"
Dynamic: author
Dynamic: author-email
Dynamic: classifier
Dynamic: description
Dynamic: description-content-type
Dynamic: home-page
Dynamic: keywords
Dynamic: license
Dynamic: license-file
Dynamic: project-url
Dynamic: provides-extra
Dynamic: requires-dist
Dynamic: summary
